.travis.yml
CONTRIBUTING.md
Dockerfile
LICENSE.txt
MANIFEST.in
README.md
mkdocs.yml
setup.cfg
setup.py
tox.ini
docs/guide_to_saber_api.md
docs/index.md
docs/installation.md
docs/quick_start.md
docs/resources.md
saber/__init__.py
saber/config.ini
saber/config.py
saber/constants.py
saber/dataset.py
saber/embeddings.py
saber/metrics.py
saber/preprocessor.py
saber/saber.py
saber/trainer.py
saber.egg-info/PKG-INFO
saber.egg-info/SOURCES.txt
saber.egg-info/dependency_links.txt
saber.egg-info/not-zip-safe
saber.egg-info/requires.txt
saber.egg-info/top_level.txt
saber/cli/__init__.py
saber/cli/app.py
saber/cli/train.py
saber/models/__init__.py
saber/models/base_model.py
saber/models/multi_task_lstm_crf.py
saber/pretrained_models/PRGE.tar.bz2
saber/tests/__init__.py
saber/tests/test_app_utils.py
saber/tests/test_base_model.py
saber/tests/test_config.py
saber/tests/test_data_utils.py
saber/tests/test_dataset.py
saber/tests/test_embeddings.py
saber/tests/test_generic_utils.py
saber/tests/test_grounding_utils.py
saber/tests/test_metrics.py
saber/tests/test_model_utils.py
saber/tests/test_multi_task_lstm_crf.py
saber/tests/test_preprocessor.py
saber/tests/test_saber.py
saber/tests/test_text_utils.py
saber/tests/test_trainer.py
saber/tests/__pycache__/__init__.cpython-36.pyc
saber/tests/__pycache__/test_app_utils.cpython-36-PYTEST.pyc
saber/tests/__pycache__/test_base_model.cpython-36-PYTEST.pyc
saber/tests/__pycache__/test_config.cpython-36-PYTEST.pyc
saber/tests/__pycache__/test_data_utils.cpython-36-PYTEST.pyc
saber/tests/__pycache__/test_dataset.cpython-36-PYTEST.pyc
saber/tests/__pycache__/test_embeddings.cpython-36-PYTEST.pyc
saber/tests/__pycache__/test_generic_utils.cpython-36-PYTEST.pyc
saber/tests/__pycache__/test_grounding_utils.cpython-36-PYTEST.pyc
saber/tests/__pycache__/test_metrics.cpython-36-PYTEST.pyc
saber/tests/__pycache__/test_model_utils.cpython-36-PYTEST.pyc
saber/tests/__pycache__/test_multi_task_lstm_crf.cpython-36-PYTEST.pyc
saber/tests/__pycache__/test_preprocessor.cpython-36-PYTEST.pyc
saber/tests/__pycache__/test_saber.cpython-36-PYTEST.pyc
saber/tests/__pycache__/test_text_utils.cpython-36-PYTEST.pyc
