Metadata-Version: 2.1
Name: saber
Version: 0.1.0
Summary: Saber: Sequence Annotator for Biomedical Entities and Relations
Home-page: https://github.com/BaderLab/saber
Author: John Giorgi
Author-email: johnmgiorgi@gmail.com
License: MIT
Keywords: Natural Language Processing,Named Entity Recognition
Platform: UNKNOWN
Classifier: Development Status :: 3 - Alpha
Classifier: Framework :: Flask
Classifier: License :: OSI Approved :: MIT License
Classifier: Programming Language :: Python :: 3 :: Only
Classifier: Programming Language :: Python :: 3.5
Classifier: Programming Language :: Python :: 3.6
Classifier: Programming Language :: Python :: 3.7
Classifier: Operating System :: OS Independent
Requires-Python: >=3.5
